pierrehrt_picsou/__init__.py
pierrehrt_picsou/picsou.py
pierrehrt_picsou-0.1.0.dist-info/METADATA
pierrehrt_picsou-0.1.0.dist-info/WHEEL
pierrehrt_picsou-0.1.0.dist-info/RECORD
