Metadata-Version: 2.1
Name: pierrehrt-picsou
Version: 0.1.0
Summary: 
Author: Pierre HOURTOULE
Author-email: pierre.hourtoule@ig2i.centralelille.fr
Requires-Python: >=3.10,<4.0
Classifier: Programming Language :: Python :: 3
Classifier: Programming Language :: Python :: 3.10
Classifier: Programming Language :: Python :: 3.11
Classifier: Programming Language :: Python :: 3.12
Requires-Dist: pillow (>=10.2.0,<11.0.0)
